[
  {
    "id": "086f7b18-534b-4f3b-a30a-4ba374752210",
    "name": "Allegria Turism SRL",
    "cui": "RO31555494",
    "city": "Oradea",
    "industry": "HoReCa",
    "contact_person": "Carmen Popa",
    "phone": "0746193071",
    "email": null,
    "status": "activ",
    "notes": null,
    "created_at": "2026-03-09T07:56:34.423446+00:00"
  },
  {
    "id": "d50602fc-d5f1-4eb6-9f6a-1db071ca76e8",
    "name": "Araly Exim SRL",
    "cui": "RO3722902",
    "city": "Oradea",
    "industry": "Comerț",
    "contact_person": "Alex Lorincz",
    "phone": "0741197309",
    "email": null,
    "status": "activ",
    "notes": null,
    "created_at": "2026-03-09T07:56:34.423923+00:00"
  },
  {
    "id": "02370ce3-0254-4869-900d-6ca9d9ace6e1",
    "name": "Babuiesti SRL",
    "cui": "RO44507065",
    "city": "Vâlcea",
    "industry": "Construcții",
    "contact_person": null,
    "phone": "0746181402",
    "email": null,
    "status": "activ",
    "notes": null,
    "created_at": "2026-03-09T07:56:34.424274+00:00"
  },
  {
    "id": "d1eece40-5565-4e72-8084-00d65002a074",
    "name": "Balearia Food SRL",
    "cui": "RO33458471",
    "city": "Oradea",
    "industry": "HoReCa",
    "contact_person": "Natalia",
    "phone": "0740134206",
    "email": null,
    "status": "activ",
    "notes": null,
    "created_at": "2026-03-09T07:56:34.424530+00:00"
  },
  {
    "id": "7fe84c7f-60c5-4501-9007-7d90091c3a43",
    "name": "Bonavilla Complex SRL",
    "cui": "RO17432589",
    "city": "Oradea",
    "industry": "HoReCa",
    "contact_person": null,
    "phone": null,
    "email": null,
    "status": "activ",
    "notes": null,
    "created_at": "2026-03-09T07:56:34.424769+00:00"
  },
  {
    "id": "226f3320-9078-4943-89f4-dcd7cd729499",
    "name": "Complex Adorianis SRL",
    "cui": "RO7629262",
    "city": "Satu Mare",
    "industry": "HoReCa",
    "contact_person": null,
    "phone": null,
    "email": null,
    "status": "activ",
    "notes": null,
    "created_at": "2026-03-09T07:56:34.425054+00:00"
  },
  {
    "id": "3e4136dd-c436-4406-972e-05108e4257d0",
    "name": "Covaliciuc Mariana",
    "cui": null,
    "city": "Bihor",
    "industry": "Agricultură",
    "contact_person": "Mariana Covaliciuc",
    "phone": null,
    "email": null,
    "status": "activ",
    "notes": null,
    "created_at": "2026-03-09T07:56:34.425267+00:00"
  },
  {
    "id": "67b736b7-6635-4787-b10b-78870b81572f",
    "name": "Da Vinci Construct Proiect SRL",
    "cui": "RO31572576",
    "city": "Oradea",
    "industry": "Construcții",
    "contact_person": null,
    "phone": null,
    "email": null,
    "status": "activ",
    "notes": null,
    "created_at": "2026-03-09T07:56:34.425473+00:00"
  },
  {
    "id": "af4f00a1-093d-4118-82f5-05dee0586dde",
    "name": "Danessa Impex SRL",
    "cui": "RO6775267",
    "city": "Oradea",
    "industry": "Comerț",
    "contact_person": null,
    "phone": null,
    "email": null,
    "status": "activ",
    "notes": null,
    "created_at": "2026-03-09T07:56:34.425662+00:00"
  },
  {
    "id": "2f709436-2892-4228-a75a-2e78a37c0079",
    "name": "Euroimpact SRL",
    "cui": "RO16536920",
    "city": "Oradea",
    "industry": "Construcții",
    "contact_person": null,
    "phone": null,
    "email": null,
    "status": "activ",
    "notes": null,
    "created_at": "2026-03-09T07:56:34.425847+00:00"
  },
  {
    "id": "ff4dc2db-8a5e-4845-aefb-c9cf80e1a341",
    "name": "FNK Garage SRL",
    "cui": "RO35892147",
    "city": "Oradea",
    "industry": "Auto",
    "contact_person": null,
    "phone": null,
    "email": null,
    "status": "activ",
    "notes": null,
    "created_at": "2026-03-09T07:56:34.426038+00:00"
  },
  {
    "id": "5dbf61d0-8d25-473b-ab7f-97f14e01f224",
    "name": "Giulio Impex SRL",
    "cui": "RO6823456",
    "city": "Oradea",
    "industry": "Comerț",
    "contact_person": null,
    "phone": null,
    "email": null,
    "status": "activ",
    "notes": null,
    "created_at": "2026-03-09T07:56:34.426214+00:00"
  },
  {
    "id": "2766b6dc-47b2-42fe-ac4a-d58b8c001363",
    "name": "Global Clean Magic SRL",
    "cui": "RO28945612",
    "city": "Oradea",
    "industry": "Servicii curățenie",
    "contact_person": null,
    "phone": null,
    "email": null,
    "status": "activ",
    "notes": null,
    "created_at": "2026-03-09T07:56:34.426408+00:00"
  },
  {
    "id": "8d883b7a-2029-46a8-9c3b-97990dcda976",
    "name": "Hortifruct SRL",
    "cui": "RO14567823",
    "city": "Oradea",
    "industry": "Agricultură",
    "contact_person": null,
    "phone": null,
    "email": null,
    "status": "activ",
    "notes": null,
    "created_at": "2026-03-09T07:56:34.426730+00:00"
  },
  {
    "id": "620034bb-05f4-4c14-969f-3275d76654ea",
    "name": "Laris Legend Food SRL",
    "cui": "RO38567412",
    "city": "Oradea",
    "industry": "HoReCa",
    "contact_person": null,
    "phone": "0722708715",
    "email": null,
    "status": "activ",
    "notes": null,
    "created_at": "2026-03-09T07:56:34.426962+00:00"
  },
  {
    "id": "60bbb9c8-b123-4865-9bd0-f4d48d8fa237",
    "name": "Lider International SRL",
    "cui": "RO15678923",
    "city": "Oradea",
    "industry": "Transport",
    "contact_person": null,
    "phone": null,
    "email": null,
    "status": "activ",
    "notes": null,
    "created_at": "2026-03-09T07:56:34.427178+00:00"
  },
  {
    "id": "f7f37b64-1922-4949-a6e1-00a00924b487",
    "name": "Novarom Tour Felix SRL",
    "cui": "RO19234567",
    "city": "Băile Felix",
    "industry": "HoReCa",
    "contact_person": null,
    "phone": null,
    "email": null,
    "status": "activ",
    "notes": null,
    "created_at": "2026-03-09T07:56:34.427367+00:00"
  },
  {
    "id": "158890c4-96f0-49b3-810b-47aee1acca7e",
    "name": "Only Build Residence SRL",
    "cui": "RO32567891",
    "city": "Oradea",
    "industry": "Construcții",
    "contact_person": null,
    "phone": null,
    "email": null,
    "status": "activ",
    "notes": null,
    "created_at": "2026-03-09T07:56:34.427557+00:00"
  },
  {
    "id": "63a81672-ef0a-4968-9d47-c8e4b8078bfb",
    "name": "Pepiniera Takacs Csaba II",
    "cui": null,
    "city": "Bihor",
    "industry": "Agricultură",
    "contact_person": "Takacs Csaba",
    "phone": null,
    "email": null,
    "status": "activ",
    "notes": null,
    "created_at": "2026-03-09T07:56:34.427735+00:00"
  },
  {
    "id": "b5445b78-0222-4033-9b09-08b88e3f9537",
    "name": "PFL Facility Services SRL",
    "cui": "RO29876543",
    "city": "Oradea",
    "industry": "Servicii curățenie",
    "contact_person": null,
    "phone": null,
    "email": null,
    "status": "activ",
    "notes": null,
    "created_at": "2026-03-09T07:56:34.427908+00:00"
  },
  {
    "id": "035f05d3-b119-4d85-a1db-9fb153054d2e",
    "name": "Premium Martin Construct SRL",
    "cui": "RO34567812",
    "city": "Oradea",
    "industry": "Construcții",
    "contact_person": null,
    "phone": null,
    "email": null,
    "status": "activ",
    "notes": null,
    "created_at": "2026-03-09T07:56:34.428095+00:00"
  },
  {
    "id": "01d3b47a-9311-40e3-9a10-0fee99f68ba3",
    "name": "Pro Smart Cleaning SRL",
    "cui": "RO36789123",
    "city": "Oradea",
    "industry": "Servicii curățenie",
    "contact_person": null,
    "phone": null,
    "email": null,
    "status": "activ",
    "notes": null,
    "created_at": "2026-03-09T07:56:34.428273+00:00"
  },
  {
    "id": "f683a3d4-067f-4f13-92e7-e360025ccee2",
    "name": "Repede Pleasure SRL",
    "cui": "RO25678934",
    "city": "Oradea",
    "industry": "HoReCa",
    "contact_person": null,
    "phone": null,
    "email": null,
    "status": "activ",
    "notes": null,
    "created_at": "2026-03-09T07:56:34.428442+00:00"
  },
  {
    "id": "6aa3e009-f2c5-495f-a93c-43e6b33b9e41",
    "name": "Semarc A-Z Construct SRL",
    "cui": "RO27891234",
    "city": "Oradea",
    "industry": "Construcții",
    "contact_person": null,
    "phone": null,
    "email": null,
    "status": "activ",
    "notes": null,
    "created_at": "2026-03-09T07:56:34.428610+00:00"
  },
  {
    "id": "36b87169-ebfe-4e54-ba31-df8568b84e2a",
    "name": "Template",
    "cui": null,
    "city": null,
    "industry": null,
    "contact_person": null,
    "phone": null,
    "email": null,
    "status": "activ",
    "notes": null,
    "created_at": "2026-03-09T07:56:34.428784+00:00"
  },
  {
    "id": "bda5af86-c460-406d-b127-1310a9df3e51",
    "name": "Cri-Taxi",
    "cui": null,
    "city": "Oradea",
    "industry": "Transport",
    "contact_person": null,
    "phone": null,
    "email": null,
    "status": "activ",
    "notes": null,
    "created_at": "2026-03-09T07:56:34.428972+00:00"
  },
  {
    "id": "15c184bf-7392-47fd-96fc-b7fb55e6ddff",
    "name": "Luca Veterinaru SRL",
    "cui": "RO39876541",
    "city": "Oradea",
    "industry": "Servicii veterinare",
    "contact_person": null,
    "phone": null,
    "email": null,
    "status": "activ",
    "notes": null,
    "created_at": "2026-03-09T07:56:34.429170+00:00"
  },
  {
    "id": "58b580d9-bf7f-4c1c-9c93-268c97783160",
    "name": "Alverosal",
    "cui": "RO41234567",
    "city": "Oradea",
    "industry": "Construcții",
    "contact_person": null,
    "phone": null,
    "email": null,
    "status": "activ",
    "notes": null,
    "created_at": "2026-03-09T07:56:34.429348+00:00"
  },
  {
    "id": "5d25cda8-0565-4e32-8c19-f60af1fc3ba6",
    "name": "Alversoal",
    "cui": null,
    "city": null,
    "industry": null,
    "contact_person": null,
    "phone": null,
    "email": null,
    "status": "activ",
    "notes": null,
    "created_at": "2026-03-09T07:56:34.429597+00:00"
  },
  {
    "id": "9010e1b1-26f6-4a9a-aeef-b40a1b1544e5",
    "name": "Leader International",
    "cui": null,
    "city": null,
    "industry": null,
    "contact_person": null,
    "phone": null,
    "email": null,
    "status": "activ",
    "notes": null,
    "created_at": "2026-03-09T07:56:34.429925+00:00"
  },
  {
    "id": "66d93819-91a4-4948-9070-5cbe6d674820",
    "name": "McNeil",
    "cui": null,
    "city": "România",
    "industry": "Construcții",
    "contact_person": null,
    "phone": null,
    "email": null,
    "status": "activ",
    "notes": null,
    "created_at": "2026-03-09T07:56:34.430182+00:00"
  },
  {
    "id": "2d75e798-a38b-4277-bf07-c4c37869976a",
    "name": "Winners",
    "cui": null,
    "city": "România",
    "industry": "HoReCa",
    "contact_person": null,
    "phone": null,
    "email": null,
    "status": "activ",
    "notes": null,
    "created_at": "2026-03-09T07:56:34.430399+00:00"
  },
  {
    "id": "717f47a5-c869-432a-a8f4-8d567f326e3a",
    "name": "D&C Fashion",
    "cui": null,
    "city": "România",
    "industry": "Textile",
    "contact_person": null,
    "phone": null,
    "email": null,
    "status": "activ",
    "notes": null,
    "created_at": "2026-03-09T07:56:34.430598+00:00"
  },
  {
    "id": "b9a4b6b9-04a5-4468-ae40-2ef700e896d4",
    "name": "Cri Taxi",
    "cui": null,
    "city": null,
    "industry": null,
    "contact_person": null,
    "phone": null,
    "email": null,
    "status": "activ",
    "notes": null,
    "created_at": "2026-03-09T07:56:34.430787+00:00"
  },
  {
    "id": "352d7688-d9fc-45b2-8ee1-9bc81fcb2956",
    "name": "Robi&Adi Construct Srl",
    "cui": null,
    "city": "România",
    "industry": "Construcții",
    "contact_person": null,
    "phone": null,
    "email": null,
    "status": "activ",
    "notes": null,
    "created_at": "2026-03-09T07:56:34.430988+00:00"
  },
  {
    "id": "972c8e23-c67e-4cf9-89fa-b32bd1c4921a",
    "name": "Hanna(Carei)",
    "cui": null,
    "city": null,
    "industry": null,
    "contact_person": null,
    "phone": null,
    "email": null,
    "status": "activ",
    "notes": null,
    "created_at": "2026-03-09T07:56:34.431191+00:00"
  },
  {
    "id": "7d0cfb23-749e-4e88-a47f-738097ee592c",
    "name": "Ina Herculane(kataleya)",
    "cui": null,
    "city": null,
    "industry": null,
    "contact_person": null,
    "phone": null,
    "email": null,
    "status": "activ",
    "notes": null,
    "created_at": "2026-03-09T07:56:34.431393+00:00"
  }
]